lgw/__init__.py
lgw/api_gateway.py
lgw/api_gateway_domain.py
lgw/lambda_bundle.py
lgw/lambda_util.py
lgw/main.py
lgw/route53.py
lgw/s3.py
lgw/settings.py
lgw/util.py
lgw/version.py
lgw-1.2.8.dist-info/LICENSE
lgw-1.2.8.dist-info/METADATA
lgw-1.2.8.dist-info/WHEEL
lgw-1.2.8.dist-info/entry_points.txt
lgw-1.2.8.dist-info/RECORD
