Metadata-Version: 2.1
Name: lgw
Version: 1.2.8
Summary: Configure an AWS Gateway in front of a Lambda function.
Home-page: https://github.com/ebridges/lgw
License: Apache-2.0
Author: Edward Q. Bridges
Author-email: ebridges@roja.cc
Requires-Python: >=3.12,<4
Classifier: License :: OSI Approved :: Apache Software License
Classifier: Programming Language :: Python :: 3
Classifier: Programming Language :: Python :: 3.12
Classifier: Programming Language :: Python :: 3.13
Classifier: Topic :: Software Development :: Build Tools
Requires-Dist: boto3 (>=1.35,<2.0)
Requires-Dist: docker (>=7.1.0,<8.0.0)
Requires-Dist: everett (>=1.0,<2.0)
Requires-Dist: moto[apigateway,lambda] (>=5.0.7,<6.0.0)
Requires-Dist: python-dotenv (>=1,<2)
Requires-Dist: tld (>=0.13,<0.14)
Project-URL: Documentation, https://github.com/ebridges/lgw/blob/master/README.md
